Workbook

Sheet Catalogo
A1: CATALOGO DE EMPLEADOS
A2: Edite esta lista y luego use: python planilla.py agregar --viernes YYYY-MM-DD
A4: Nombre Completo | B4: Tipo de Pago | C4: Salario Fijo (₡)
A5: Juan Perez | B5: Tarjeta
A6: Maria Lopez | B6: Efectivo

Sheet Resumen Mensual
A1: RESUMEN MENSUAL DE PLANILLA
A2: Totales acumulados del mes por empleado
A4: Empleado | B4: Semana | C4: Hrs Diurnas | D4: Hrs Nocturnas | E4: Hrs Mixtas | F4: Hrs Totales | G4: Salario Bruto | H4: Rebajos | I4: Seguro | J4: Neto a Pagar
A5: PAGO POR TARJETA
A6: Juan Perez | B6: Semana 10 | C6: ='Semana 10'!J9 | D6: ='Semana 10'!J10 | E6: ='Semana 10'!J11 | F6: ='Semana 10'!J13 | G6: ='Semana 10'!L9 | H6: ='Semana 10'!R9-'Semana 10'!Q9 | I6: 0 | J6: =G6-H6
B7: TOTAL MENSUAL | C7: =SUM(C6:C6) | D7: =SUM(D6:D6) | E7: =SUM(E6:E6) | F7: =SUM(F6:F6) | G7: =SUM(G6:G6) | H7: =SUM(H6:H6) | I7: 10498 | J7: =G7-H7-I7
A8: TOTAL PAGO POR TARJETA | C8: =SUMIF(B6:B7, "TOTAL MENSUAL", C6:C7) | D8: =SUMIF(B6:B7, "TOTAL MENSUAL", D6:D7) | E8: =SUMIF(B6:B7, "TOTAL MENSUAL", E6:E7) | F8: =SUMIF(B6:B7, "TOTAL MENSUAL", F6:F7) | G8: =SUMIF(B6:B7, "TOTAL MENSUAL", G6:G7) | H8: =SUMIF(B6:B7, "TOTAL MENSUAL", H6:H7) | I8: =SUMIF(B6:B7, "TOTAL MENSUAL", I6:I7) | J8: =SUMIF(B6:B7, "TOTAL MENSUAL", J6:J7)
A10: PAGO EN EFECTIVO
A11: Maria Lopez | B11: Semana 10 | C11: ='Semana 10'!J20 | D11: ='Semana 10'!J21 | E11: ='Semana 10'!J22 | F11: ='Semana 10'!J24 | G11: ='Semana 10'!L20 | H11: ='Semana 10'!R20-'Semana 10'!Q20 | I11: 0 | J11: =G11-H11
B12: TOTAL MENSUAL | C12: =SUM(C11:C11) | D12: =SUM(D11:D11) | E12: =SUM(E11:E11) | F12: =SUM(F11:F11) | G12: =SUM(G11:G11) | H12: =SUM(H11:H11) | I12: 10498 | J12: =G12-H12-I12
A13: TOTAL PAGO EN EFECTIVO | C13: =SUMIF(B11:B12, "TOTAL MENSUAL", C11:C12) | D13: =SUMIF(B11:B12, "TOTAL MENSUAL", D11:D12) | E13: =SUMIF(B11:B12, "TOTAL MENSUAL", E11:E12) | F13: =SUMIF(B11:B12, "TOTAL MENSUAL", F11:F12) | G13: =SUMIF(B11:B12, "TOTAL MENSUAL", G11:G12) | H13: =SUMIF(B11:B12, "TOTAL MENSUAL", H11:H12) | I13: =SUMIF(B11:B12, "TOTAL MENSUAL", I11:I12) | J13: =SUMIF(B11:B12, "TOTAL MENSUAL", J11:J12)
A15: GRAN TOTAL MENSUAL | C15: =C8+C13 | D15: =D8+D13 | E15: =E8+E13 | F15: =F8+F13 | G15: =G8+G13 | H15: =H8+H13 | I15: =I8+I13 | J15: =J8+J13

Sheet Dashboard
A1: DASHBOARD - RESUMEN GRAFICO DEL MES
A2: Semanas procesadas: 0
A4: DATOS POR SEMANA
A5: Semana | B5: Bruto | C5: Neto
A14: TOTALES DEL MES | F14: DISTRIBUCION DE METODO DE PAGO
A15: Total Bruto | B15: ='Resumen Mensual'!G15 | F15: Metodo | G15: Total Neto
A16: Tot. Rebajos | B16: ='Resumen Mensual'!H15 | F16: PAGO POR TARJETA | G16: ='Resumen Mensual'!J8
A17: Tot. Seguros | B17: ='Resumen Mensual'!I15 | F17: PAGO EN EFECTIVO | G17: ='Resumen Mensual'!J13
A18: TOTAL NETO | B18: ='Resumen Mensual'!J15

Sheet Semana 10
A1: PLANILLA DE PAGO SEMANAL
A2: PERIODO: | C2: 46087 | D2: a | E2: =$C$2+6 | G2: Semana #10
A3: TARIFAS (₡/hora): | C3: Diurna: | D3: 50 | E3: Tarifa Mixta: | F3: 62.5 | G3: Tarifa Noct: | H3: 75 | I3: Tarifa Extra: | J3: =$D$3*1.5
A5: PAGO POR TARJETA
C6: HORAS POR JORNADA | L6: DEDUCCION / RESUMEN SEMANAL
A7: Empleado | B7: Jornada | C7: Viernes | D7: Sabado | E7: Domingo | F7: Lunes | G7: Martes | H7: Miercoles | I7: Jueves | J7: TOTAL | L7: Bruto | M7: Prestamo | N7: Combust. | O7: Mercad. | P7: Adelanto | Q7: Seguro | R7: Tot.Ded. | S7: NETO
B8: Fecha: | C8: =$C$2+0 | D8: =$C$2+1 | E8: =$C$2+2 | F8: =$C$2+3 | G8: =$C$2+4 | H8: =$C$2+5 | I8: =$C$2+6
A9: Juan Perez | B9: Hrs. Diurnas | J9: =C9+D9+E9+F9+G9+H9+I9 | L9: =J9*$D$3+J10*$F$3+J11*$H$3+J12*$J$3 | Q9: 10498 | R9: =SUM(M9:Q9) | S9: =L9-R9
B10: Hrs. Mixtas | J10: =C10+D10+E10+F10+G10+H10+I10
B11: Hrs. Nocturnas | J11: =C11+D11+E11+F11+G11+H11+I11
B12: Hrs. Extra | J12: =C12+D12+E12+F12+G12+H12+I12
B13: TOTAL HORAS | C13: =C9+C10+C11+C12 | D13: =D9+D10+D11+D12 | E13: =E9+E10+E11+E12 | F13: =F9+F10+F11+F12 | G13: =G9+G10+G11+G12 | H13: =H9+H10+H11+H12 | I13: =I9+I10+I11+I12 | J13: =C13+D13+E13+F13+G13+H13+I13
A14: TOTAL PAGO POR TARJETA | L14: =L9 | M14: =M9 | N14: =N9 | O14: =O9 | P14: =P9 | Q14: =Q9 | R14: =R9 | S14: =L14-R14
A16: PAGO EN EFECTIVO
C17: HORAS POR JORNADA | L17: DEDUCCION / RESUMEN SEMANAL
A18: Empleado | B18: Jornada | C18: Viernes | D18: Sabado | E18: Domingo | F18: Lunes | G18: Martes | H18: Miercoles | I18: Jueves | J18: TOTAL | L18: Bruto | M18: Prestamo | N18: Combust. | O18: Mercad. | P18: Adelanto | Q18: Seguro | R18: Tot.Ded. | S18: NETO
B19: Fecha: | C19: =$C$2+0 | D19: =$C$2+1 | E19: =$C$2+2 | F19: =$C$2+3 | G19: =$C$2+4 | H19: =$C$2+5 | I19: =$C$2+6
A20: Maria Lopez | B20: Hrs. Diurnas | J20: =C20+D20+E20+F20+G20+H20+I20 | L20: =J20*$D$3+J21*$F$3+J22*$H$3+J23*$J$3 | Q20: 10498 | R20: =SUM(M20:Q20) | S20: =L20-R20
B21: Hrs. Mixtas | J21: =C21+D21+E21+F21+G21+H21+I21
B22: Hrs. Nocturnas | J22: =C22+D22+E22+F22+G22+H22+I22
B23: Hrs. Extra | J23: =C23+D23+E23+F23+G23+H23+I23
B24: TOTAL HORAS | C24: =C20+C21+C22+C23 | D24: =D20+D21+D22+D23 | E24: =E20+E21+E22+E23 | F24: =F20+F21+F22+F23 | G24: =G20+G21+G22+G23 | H24: =H20+H21+H22+H23 | I24: =I20+I21+I22+I23 | J24: =C24+D24+E24+F24+G24+H24+I24
A25: TOTAL PAGO EN EFECTIVO | L25: =L20 | M25: =M20 | N25: =N20 | O25: =O20 | P25: =P20 | Q25: =Q20 | R25: =R20 | S25: =L25-R25
A28: GRAN TOTAL DE LA SEMANA | L28: =L14+L25 | M28: =M14+M25 | N28: =N14+N25 | O28: =O14+O25 | P28: =P14+P25 | Q28: =Q14+Q25 | R28: =R14+R25 | S28: =L28-R28

Sheet Res. Sem. 10
A1: RESUMEN SEMANAL - Semana 10
A2: 06/03/2026 → 12/03/2026
A4: Empleado | B4: Hrs Diurnas | C4: Hrs Mixtas | D4: Hrs Nocturnas | E4: Total Hrs | F4: Bruto (₡) | G4: Rebajos (₡) | H4: Seguro (₡) | I4: NETO (₡)
A5: PAGO POR TARJETA
A6: Juan Perez | B6: ='Semana 10'!J9 | C6: ='Semana 10'!J10 | D6: ='Semana 10'!J11 | E6: ='Semana 10'!J13 | F6: ='Semana 10'!L9 | G6: ='Semana 10'!R9-'Semana 10'!Q9 | H6: ='Semana 10'!Q9 | I6: ='Semana 10'!S9
A7: TOTAL PAGO POR TARJETA | B7: =SUM(B6:B6) | C7: =SUM(C6:C6) | D7: =SUM(D6:D6) | E7: =SUM(E6:E6) | F7: =SUM(F6:F6) | G7: =SUM(G6:G6) | H7: =SUM(H6:H6) | I7: =SUM(I6:I6)
A9: PAGO EN EFECTIVO
A10: Maria Lopez | B10: ='Semana 10'!J20 | C10: ='Semana 10'!J21 | D10: ='Semana 10'!J22 | E10: ='Semana 10'!J24 | F10: ='Semana 10'!L20 | G10: ='Semana 10'!R20-'Semana 10'!Q20 | H10: ='Semana 10'!Q20 | I10: ='Semana 10'!S20
A11: TOTAL PAGO EN EFECTIVO | B11: =SUM(B10:B10) | C11: =SUM(C10:C10) | D11: =SUM(D10:D10) | E11: =SUM(E10:E10) | F11: =SUM(F10:F10) | G11: =SUM(G10:G10) | H11: =SUM(H10:H10) | I11: =SUM(I10:I10)
A13: GRAN TOTAL SEMANAL | B13: =B7+B11 | C13: =C7+C11 | D13: =D7+D11 | E13: =E7+E11 | F13: =F7+F11 | G13: =G7+G11 | H13: =H7+H11 | I13: =I7+I11
